LICENSE
MANIFEST.in
README.md
setup.py
wine_deamonizer/__init__.py
wine_deamonizer.egg-info/PKG-INFO
wine_deamonizer.egg-info/SOURCES.txt
wine_deamonizer.egg-info/dependency_links.txt
wine_deamonizer.egg-info/top_level.txt