Metadata-Version: 1.1
Name: wine-deamonizer
Version: 1.0.0
Summary: Run Windows processes under Wine as Unix daemons.
Home-page: https://github.com/oblalex/Wine-deamonizer
Author: Alexander Oblovatniy
Author-email: oblovatniy@gmail.com
License: GPLv2
Platform: UNKNOWN
Classifier: Development Status :: 5 - Production/Stable
Classifier: Intended Audience :: Developers
Classifier: License :: Free for non-commercial use
Classifier: Natural Language :: English
Classifier: Operating System :: OS Independent
Classifier: Programming Language :: Python :: 2.7
Classifier: Topic :: Software Development :: Libraries
